{
    "m_Version": 4,
    "DisplayName": "Meat",
    "Items": [
        {
            "ClassName": "ChickenBreastMeat",
            "MaxPriceThreshold": 20,
            "MinPriceThreshold": 20,
            "MaxStockThreshold": 1,
            "MinStockThreshold": 1,
            "PurchaseType": 0,
            "SpawnAttachments": [],
            "Variants": []
        },
		{
            "ClassName": "GoatSteakMeat",
            "MaxPriceThreshold": 20,
            "MinPriceThreshold": 20,
            "MaxStockThreshold": 1,
            "MinStockThreshold": 1,
            "PurchaseType": 0,
            "SpawnAttachments": [],
            "Variants": []
        },
		{
            "ClassName": "SheepSteakMeat",
            "MaxPriceThreshold": 20,
            "MinPriceThreshold": 20,
            "MaxStockThreshold": 1,
            "MinStockThreshold": 1,
            "PurchaseType": 0,
            "SpawnAttachments": [],
            "Variants": []
        },
		{
            "ClassName": "PigSteakMeat",
            "MaxPriceThreshold": 20,
            "MinPriceThreshold": 20,
            "MaxStockThreshold": 1,
            "MinStockThreshold": 1,
            "PurchaseType": 0,
            "SpawnAttachments": [],
            "Variants": []
        },
		{
            "ClassName": "BoarSteakMeat",
            "MaxPriceThreshold": 20,
            "MinPriceThreshold": 20,
            "MaxStockThreshold": 1,
            "MinStockThreshold": 1,
            "PurchaseType": 0,
            "SpawnAttachments": [],
            "Variants": []
        },
		{
            "ClassName": "WolfSteakMeat",
            "MaxPriceThreshold": 30,
            "MinPriceThreshold": 30,
            "MaxStockThreshold": 1,
            "MinStockThreshold": 1,
            "PurchaseType": 0,
            "SpawnAttachments": [],
            "Variants": []
        },
		{
            "ClassName": "DeerSteakMeat",
            "MaxPriceThreshold": 20,
            "MinPriceThreshold": 20,
            "MaxStockThreshold": 1,
            "MinStockThreshold": 1,
            "PurchaseType": 0,
            "SpawnAttachments": [],
            "Variants": []
        },
		{
            "ClassName": "CowSteakMeat",
            "MaxPriceThreshold": 20,
            "MinPriceThreshold": 20,
            "MaxStockThreshold": 1,
            "MinStockThreshold": 1,
            "PurchaseType": 0,
            "SpawnAttachments": [],
            "Variants": []
        },
		{
            "ClassName": "BearSteakMeat",
            "MaxPriceThreshold": 50,
            "MinPriceThreshold": 50,
            "MaxStockThreshold": 1,
            "MinStockThreshold": 1,
            "PurchaseType": 0,
            "SpawnAttachments": [],
            "Variants": []
        }
    ]
}