{
    "m_Version": 8,
    "DisplayName": "Tools (big)",
    "Icon": "Deliver",
    "Color": "",
    "InitStockPercent": 75.0,
    "Items": [
        {
            "ClassName": "lugwrench",
            "MaxPriceThreshold": 300,
            "MinPriceThreshold": 300,
            "SellPricePercent": -1,
            "MaxStockThreshold": 1,
            "MinStockThreshold": 1,
            "SpawnAttachments": [],
            "Variants": []
        },
        {
            "ClassName": "crowbar",
            "MaxPriceThreshold": 300,
            "MinPriceThreshold": 300,
            "SellPricePercent": -1,
            "MaxStockThreshold": 1,
            "MinStockThreshold": 1,
            "SpawnAttachments": [],
            "Variants": []
        },
        {
            "ClassName": "shovel",
            "MaxPriceThreshold": 300,
            "MinPriceThreshold": 300,
            "SellPricePercent": -1,
            "MaxStockThreshold": 1,
            "MinStockThreshold": 1,
            "SpawnAttachments": [],
            "Variants": []
        },
        {
            "ClassName": "pickaxe",
            "MaxPriceThreshold": 400,
            "MinPriceThreshold": 400,
            "SellPricePercent": -1,
            "MaxStockThreshold": 1,
            "MinStockThreshold": 1,
            "SpawnAttachments": [],
            "Variants": []
        },
        {
            "ClassName": "sledgehammer",
            "MaxPriceThreshold": 400,
            "MinPriceThreshold": 400,
            "SellPricePercent": -1,
            "MaxStockThreshold": 1,
            "MinStockThreshold": 1,
            "SpawnAttachments": [],
            "Variants": []
        },
        {
            "ClassName": "woodaxe",
            "MaxPriceThreshold": 500,
            "MinPriceThreshold": 500,
            "SellPricePercent": -1,
            "MaxStockThreshold": 1,
            "MinStockThreshold": 1,
            "SpawnAttachments": [],
            "Variants": []
        },
        {
            "ClassName": "firefighteraxe",
            "MaxPriceThreshold": 600,
            "MinPriceThreshold": 600,
            "SellPricePercent": -1,
            "MaxStockThreshold": 1,
            "MinStockThreshold": 1,
            "SpawnAttachments": [],
            "Variants": []
        }
    ]
}